{
  "type": "tlotd:witching",
  "ingredients": [
    {
      "item": "minecraft:rotten_flesh"
    },
    {
      "item": "minecraft:sugar"
    },
    {
      "item": "tlotd:mistletoe"
    },
    {
      "item": "tlotd:edelweiss_petals"
    },
    {
      "item": "minecraft:rotten_flesh"
    },
    {
      "item": "minecraft:rotten_flesh"
    },
    {
      "item": "minecraft:rotten_flesh"
    },
    {
      "item": "minecraft:rotten_flesh"
    },
    {
      "item": "minecraft:rotten_flesh"
    }
  ],
  "output": {
    "count": 6,
    "item": "tlotd:cured_meat"
  }
}